setup.py
flowdock/__init__.py
flowdock/exceptions.py
flowdock/push.py
flowdock/streaming.py
flowdock/helpers/__init__.py
flowdock/helpers/log.py
pyflowdock.egg-info/PKG-INFO
pyflowdock.egg-info/SOURCES.txt
pyflowdock.egg-info/dependency_links.txt
pyflowdock.egg-info/requires.txt
pyflowdock.egg-info/top_level.txt